Metadata-Version: 1.0
Name: gorillaz
Version: 0.1
Summary: Test Gaussian distributions
Home-page: UNKNOWN
Author: UNKNOWN
Author-email: UNKNOWN
License: UNKNOWN
Platform: UNKNOWN
